qg_botsdk/__init__.py
qg_botsdk/_api_model.py
qg_botsdk/_event.py
qg_botsdk/_exception.py
qg_botsdk/_proto_events_conversion.py
qg_botsdk/_queue.py
qg_botsdk/_seq_cache.py
qg_botsdk/_session.py
qg_botsdk/_statics.py
qg_botsdk/_utils.py
qg_botsdk/api.py
qg_botsdk/api_model.py
qg_botsdk/async_api.py
qg_botsdk/http.py
qg_botsdk/logger.py
qg_botsdk/model.py
qg_botsdk/plugins.py
qg_botsdk/qg_bot.py
qg_botsdk/qg_bot_proto.py
qg_botsdk/sandbox.py
qg_botsdk/session.py
qg_botsdk/utils.py
qg_botsdk/version.py
qg_botsdk/proto/__init__.py
qg_botsdk/proto/abc_proto.py
qg_botsdk/proto/proto.py
qg_botsdk/proto/proto_remote_wh.py
qg_botsdk/proto/proto_wh.py
qg_botsdk/proto/proto_ws.py
qg_botsdk/proto/wh_backend/__init__.py
qg_botsdk/proto/wh_backend/wh_core.py
qg_botsdk/proto/wh_backend/ed25519/__init__.py
qg_botsdk/proto/wh_backend/ed25519/ed25519.py
qg_botsdk/proto/wh_backend/ed25519/edwards25519.py
qg_botsdk-4.3.8.dist-info/licenses/LICENSE
test/__init__.py
test/_base_context.py
test/_testing_plugin.py
test/conftest.py
test/test_api.py
test/test_base.py
test/test_run.py
test/test_session.py
qg_botsdk-4.3.8.dist-info/METADATA
qg_botsdk-4.3.8.dist-info/WHEEL
qg_botsdk-4.3.8.dist-info/top_level.txt
qg_botsdk-4.3.8.dist-info/RECORD
