Metadata-Version: 2.4
Name: qg-botsdk
Version: 4.3.8
Summary: easy-to-use SDK for Tencent QQ guild robot
Home-page: https://github.com/GLGDLY/qg_botsdk
Author: GDLY
Author-email: tzlgdly@gmail.com
Keywords: sample,example,setuptools
Classifier: Programming Language :: Python :: 3
Classifier: License :: OSI Approved :: MIT License
Classifier: Operating System :: OS Independent
Classifier: Intended Audience :: Developers
Classifier: Topic :: Software Development :: Build Tools
Requires-Python: <4,>=3.7
License-File: LICENSE
Requires-Dist: aiohttp<4,>=3.8.1
Dynamic: classifier
Dynamic: description
Dynamic: license-file
